streamlit_disqus/__init__.py
streamlit_disqus/frontend/build/asset-manifest.json
streamlit_disqus/frontend/build/bootstrap.min.css
streamlit_disqus/frontend/build/index.html
streamlit_disqus/frontend/build/precache-manifest.c64caa5f7d5eee0d36dc0df937473e7b.js
streamlit_disqus/frontend/build/precache-manifest.e981875631eb21c05b0047283e88fc2f.js
streamlit_disqus/frontend/build/service-worker.js
streamlit_disqus/frontend/build/static/js/2.262829b5.chunk.js
streamlit_disqus/frontend/build/static/js/2.262829b5.chunk.js.LICENSE.txt
streamlit_disqus/frontend/build/static/js/2.262829b5.chunk.js.map
streamlit_disqus/frontend/build/static/js/main.00ee2387.chunk.js
streamlit_disqus/frontend/build/static/js/main.00ee2387.chunk.js.map
streamlit_disqus/frontend/build/static/js/main.24565fd4.chunk.js
streamlit_disqus/frontend/build/static/js/main.24565fd4.chunk.js.map
streamlit_disqus/frontend/build/static/js/runtime-main.9bcd1319.js
streamlit_disqus/frontend/build/static/js/runtime-main.9bcd1319.js.map
streamlit_disqus-0.1.3.dist-info/LICENSE
streamlit_disqus-0.1.3.dist-info/METADATA
streamlit_disqus-0.1.3.dist-info/WHEEL
streamlit_disqus-0.1.3.dist-info/top_level.txt
streamlit_disqus-0.1.3.dist-info/RECORD
