Metadata-Version: 2.1
Name: streamlit-disqus
Version: 0.1.3
Summary: A streamlit component to embed Disqus in your applications.
Home-page: https://github.com/okld/streamlit-disqus
Author: okld
Author-email: 
License: UNKNOWN
Platform: UNKNOWN
Requires-Python: >=3.6
